cq/__init__.py
cq/admin.py
cq/apps.py
cq/consumers.py
cq/decorators.py
cq/managers.py
cq/models.py
cq/router.py
cq/routing.py
cq/scheduler.py
cq/serializers.py
cq/signals.py
cq/signature.py
cq/task.py
cq/tasks.py
cq/utils.py
cq/views.py
cq/management/__init__.py
cq/management/commands/__init__.py
cq/management/commands/cq_check_lost.py
cq/management/commands/cq_clear_logs.py
cq/management/commands/cq_load_test.py
cq/management/commands/cq_maintenance.py
cq/management/commands/cq_retry.py
cq/management/commands/cq_runworker.py
cq/migrations/0001_initial.py
cq/migrations/0002_add_repeating.py
cq/migrations/0003_auto_20160911_0749.py
cq/migrations/0004_task_retries.py
cq/migrations/0005_task_last_retry.py
cq/migrations/0006_task_force_chain.py
cq/migrations/0007_auto_20161010_1635.py
cq/migrations/__init__.py
cq/tests/__init__.py
cq/tests/test_base.py
cq/tests/test_force_chain.py
cq/tests/test_logs.py
django_cq-0.3.3.dist-info/METADATA
django_cq-0.3.3.dist-info/WHEEL
django_cq-0.3.3.dist-info/top_level.txt
django_cq-0.3.3.dist-info/RECORD
