Metadata-Version: 2.1
Name: django-cq
Version: 0.3.3
Summary: Distributed tasks for Django Channels.
Home-page: https://github.com/uptick/django-cq
Author: Luke Hodkinson
Author-email: luke.hodkinson@uptickhq.com
Maintainer: Uptick
Maintainer-email: dev@uptickhq.com
License: BSD
Platform: UNKNOWN
Classifier: Development Status :: 3 - Alpha
Classifier: Framework :: Django
Classifier: Intended Audience :: Developers
Classifier: License :: OSI Approved :: BSD License
Classifier: Natural Language :: English
Classifier: Operating System :: OS Independent
Classifier: Programming Language :: Python
Requires-Dist: setuptools
Requires-Dist: six
Requires-Dist: croniter
Requires-Dist: channels (>=2.1.0)
Requires-Dist: channels-redis (>=2.3.0)
